ntfy_notify/__init__.py
ntfy_notify/core.py
ntfy_notify-0.1.8.dist-info/LICENSE
ntfy_notify-0.1.8.dist-info/METADATA
ntfy_notify-0.1.8.dist-info/WHEEL
ntfy_notify-0.1.8.dist-info/entry_points.txt
ntfy_notify-0.1.8.dist-info/RECORD
