Metadata-Version: 2.3
Name: ntfy-notify
Version: 0.1.8
Summary: A Python package for sending notifications via the very fabolous ntfy from CLI or Python code with stored credentials
License: EUPL-1.2
Author: Melchior im Dreital
Author-email: Melchior.im.Dreital@protonmail.com
Requires-Python: >=3.13
Classifier: Development Status :: 4 - Beta
Classifier: Intended Audience :: Developers
Classifier: Intended Audience :: System Administrators
Classifier: License :: OSI Approved :: European Union Public Licence 1.2 (EUPL 1.2)
Classifier: Programming Language :: Python :: 3
Classifier: Programming Language :: Python :: 3.13
Classifier: Topic :: Communications
Classifier: Topic :: System :: Monitoring
Classifier: Topic :: Utilities
Provides-Extra: dev
Requires-Dist: click (>=8.0.0)
Requires-Dist: pytest (>=7.0.0) ; extra == "dev"
Requires-Dist: pytest-cov (>=4.0.0) ; extra == "dev"
Requires-Dist: requests (>=2.25.0)
Project-URL: Changelog, https://gitlab.com/pynpakken/ntfy-notify/blob/main/CHANGELOG.md
Project-URL: Documentation, https://gitlab.com/pynpakken/ntfy-notify#readme
Project-URL: Homepage, https://gitlab.com/pynpakken/ntfy-notify
Project-URL: Repository, https://gitlab.com/pynpakken/ntfy-notify
